datastore/__init__.py
datastore/aggregates.py
datastore/cli.py
datastore/config.py
datastore/idempotency.py
datastore/job_tracking.py
datastore/queries_signals.py
datastore/reads.py
datastore/timescale_policies.py
datastore/writes.py
datastore/writes_signals.py
datastore/jobs/__init__.py
datastore/jobs/tick_analytics.py
datastore/jobs/tick_export.py
datastore/service/app.py
market_data_store/__init__.py
market_data_store/coordinator/__init__.py
market_data_store/coordinator/dlq.py
market_data_store/coordinator/feedback.py
market_data_store/coordinator/http_broadcast.py
market_data_store/coordinator/metrics.py
market_data_store/coordinator/policy.py
market_data_store/coordinator/queue.py
market_data_store/coordinator/settings.py
market_data_store/coordinator/types.py
market_data_store/coordinator/worker.py
market_data_store/coordinator/write_coordinator.py
market_data_store/ingestion/__init__.py
market_data_store/metrics/__init__.py
market_data_store/metrics/registry.py
market_data_store/pulse/__init__.py
market_data_store/pulse/config.py
market_data_store/pulse/publisher.py
market_data_store/queries/__init__.py
market_data_store/schema/__init__.py
market_data_store/sinks/__init__.py
market_data_store/sinks/bars_sink.py
market_data_store/sinks/base.py
market_data_store/sinks/fundamentals_sink.py
market_data_store/sinks/news_sink.py
market_data_store/sinks/options_sink.py
market_data_store/telemetry/__init__.py
market_data_store/telemetry/drift_reporter.py
mds_client/__init__.py
mds_client/aclient.py
mds_client/batch.py
mds_client/cli.py
mds_client/client.py
mds_client/errors.py
mds_client/health.py
mds_client/models.py
mds_client/rls.py
mds_client/runtime.py
mds_client/sql.py
mds_client/utils.py
market_data_store-0.6.73.dist-info/METADATA
market_data_store-0.6.73.dist-info/WHEEL
market_data_store-0.6.73.dist-info/entry_points.txt
market_data_store-0.6.73.dist-info/top_level.txt
market_data_store-0.6.73.dist-info/RECORD
