Metadata-Version: 2.4
Name: market-data-store
Version: 0.6.73
Summary: Data store control-plane (schema, migrations, policies, ops) for market-data.
Requires-Python: >=3.11
Requires-Dist: market-data-core<2.0.0,>=1.4.61
Requires-Dist: fastapi>=0.115
Requires-Dist: uvicorn[standard]>=0.30
Requires-Dist: sqlalchemy>=2.0
Requires-Dist: asyncpg>=0.29
Requires-Dist: alembic>=1.13
Requires-Dist: psycopg2-binary>=2.9
Requires-Dist: psycopg[binary]>=3.2
Requires-Dist: psycopg-pool>=3.2
Requires-Dist: typer>=0.12
Requires-Dist: pydantic>=2.7
Requires-Dist: pydantic-settings>=2.0
Requires-Dist: python-dotenv>=1.0
Requires-Dist: prometheus-client>=0.20
Requires-Dist: loguru>=0.7
Provides-Extra: dev
Requires-Dist: ruff>=0.13.2; extra == "dev"
Requires-Dist: black>=25.9.0; extra == "dev"
Requires-Dist: pre-commit>=4.3.0; extra == "dev"
Requires-Dist: jsonschema>=4.0; extra == "dev"
Requires-Dist: pytest>=7.0; extra == "dev"
Requires-Dist: pytest-asyncio>=0.21; extra == "dev"
Requires-Dist: pytest-timeout>=2.1; extra == "dev"
